googleslides/__init__.py
googleslides/exceptions.py
googleslides/googleslides.py
googleslides/cli/__init__.py
googleslides/cli/authtest.py
googleslides/cli/create_from_csv.py
googleslides/cli/create_from_yaml.py
shipyard_googleslides-0.0.5.dist-info/METADATA
shipyard_googleslides-0.0.5.dist-info/WHEEL
shipyard_googleslides-0.0.5.dist-info/top_level.txt
shipyard_googleslides-0.0.5.dist-info/RECORD
